{
  "schema": [
    {
      "name": "<8C7DD24D>",
      "type": 9
    },
    {
      "name": "<554EE944>",
      "type": 2
    },
    {
      "name": "<DBAF43F0>",
      "type": 7
    }
  ],
  "rows": [
    {
      "$id": 1,
      "<8C7DD24D>": "<529CBF51>",
      "<554EE944>": 124,
      "<DBAF43F0>": "Ouroboros...?"
    },
    {
      "$id": 2,
      "<8C7DD24D>": "<7949CD01>",
      "<554EE944>": 124,
      "<DBAF43F0>": "Ouroboros, yeah."
    },
    {
      "$id": 3,
      "<8C7DD24D>": "<5BDC90F5>",
      "<554EE944>": 124,
      "<DBAF43F0>": "So *they're* Ouroboros?"
    },
    {
      "$id": 4,
      "<8C7DD24D>": "<3FB3B700>",
      "<554EE944>": 124,
      "<DBAF43F0>": "And they're from Keves and Agnus...?"
    },
    {
      "$id": 5,
      "<8C7DD24D>": "<C1CE7A88>",
      "<554EE944>": 124,
      "<DBAF43F0>": "But they're just a bunch o' kids!"
    },
    {
      "$id": 6,
      "<8C7DD24D>": "<2D36BA1B>",
      "<554EE944>": 124,
      "<DBAF43F0>": "Watch yourselves! They could be secret spies!"
    },
    {
      "$id": 7,
      "<8C7DD24D>": "<59939BFF>",
      "<554EE944>": 124,
      "<DBAF43F0>": "It's over... This place'll be a warzone."
    },
    {
      "$id": 8,
      "<8C7DD24D>": "<343B3EF9>",
      "<554EE944>": 124,
      "<DBAF43F0>": "They're all whispering about us..."
    },
    {
      "$id": 9,
      "<8C7DD24D>": "<EDB1B579>",
      "<554EE944>": 124,
      "<DBAF43F0>": "I feel...we're not exactly welcome here."
    },
    {
      "$id": 10,
      "<8C7DD24D>": "<516BA3FA>",
      "<554EE944>": 124,
      "<DBAF43F0>": "\"Uninvited guests\", one might say."
    },
    {
      "$id": 11,
      "<8C7DD24D>": "<AB335B76>",
      "<554EE944>": 124,
      "<DBAF43F0>": "They're the ones who led us here."
    },
    {
      "$id": 12,
      "<8C7DD24D>": "<C89373DC>",
      "<554EE944>": 124,
      "<DBAF43F0>": "Oh, hey..."
    },
    {
      "$id": 13,
      "<8C7DD24D>": "<4203CDA6>",
      "<554EE944>": 124,
      "<DBAF43F0>": "Doesn't she look similar to\nthe Moebius we fought at Colony 4?"
    },
    {
      "$id": 14,
      "<8C7DD24D>": "<2B9FB779>",
      "<554EE944>": 124,
      "<DBAF43F0>": "It true... Wrinkly prunefaces abound here!"
    },
    {
      "$id": 15,
      "<8C7DD24D>": "<65F4D7E4>",
      "<554EE944>": 124,
      "<DBAF43F0>": "Manana spy tiny people too!"
    },
    {
      "$id": 16,
      "<8C7DD24D>": "<C726EB02>",
      "<554EE944>": 124,
      "<DBAF43F0>": "Is whole undiscovered race!"
    },
    {
      "$id": 17,
      "<8C7DD24D>": "<F2721C60>",
      "<554EE944>": 124,
      "<DBAF43F0>": "No... They must be...humans just like us."
    },
    {
      "$id": 18,
      "<8C7DD24D>": "<446FAE2B>",
      "<554EE944>": 124,
      "<DBAF43F0>": "So you're Ouroboros, eh?"
    },
    {
      "$id": 19,
      "<8C7DD24D>": "<75BD807E>",
      "<554EE944>": 124,
      "<DBAF43F0>": "Huh?"
    },
    {
      "$id": 20,
      "<8C7DD24D>": "<FB57B971>",
      "<554EE944>": 124,
      "<DBAF43F0>": "You've got what, one or two years left?\nSome hope you are."
    },
    {
      "$id": 21,
      "<8C7DD24D>": "<C4608908>",
      "<554EE944>": 124,
      "<DBAF43F0>": "Dunno why Vandham wasted that power\non you... What was he thinking?"
    },
    {
      "$id": 22,
      "<8C7DD24D>": "<91DA30BA>",
      "<554EE944>": 124,
      "<DBAF43F0>": "[ML:undisp ](breath, mild upset)"
    },
    {
      "$id": 23,
      "<8C7DD24D>": "<EAF06AA9>",
      "<554EE944>": 124,
      "<DBAF43F0>": "What's your problem?!"
    },
    {
      "$id": 24,
      "<8C7DD24D>": "<439CA8B4>",
      "<554EE944>": 124,
      "<DBAF43F0>": "Mind your manners!"
    },
    {
      "$id": 25,
      "<8C7DD24D>": "<A2FAFB75>",
      "<554EE944>": 124,
      "<DBAF43F0>": "Lemme introduce ya."
    },
    {
      "$id": 26,
      "<8C7DD24D>": "<90E649EB>",
      "<554EE944>": 124,
      "<DBAF43F0>": "These were our Ouroboros candidates."
    },
    {
      "$id": 27,
      "<8C7DD24D>": "<64B71EC6>",
      "<554EE944>": 124,
      "<DBAF43F0>": "They trained relentlessly to fight against\nMoebius... Each and every one of them."
    },
    {
      "$id": 28,
      "<8C7DD24D>": "<B895809A>",
      "<554EE944>": 124,
      "<DBAF43F0>": "That includes Shania there."
    },
    {
      "$id": 29,
      "<8C7DD24D>": "<E1123F8B>",
      "<554EE944>": 124,
      "<DBAF43F0>": "Candidates?"
    },
    {
      "$id": 30,
      "<8C7DD24D>": "<1C3CDC33>",
      "<554EE944>": 124,
      "<DBAF43F0>": "You happy?\nThat you stole Ouroboros from us?"
    },
    {
      "$id": 31,
      "<8C7DD24D>": "<CB38C4FF>",
      "<554EE944>": 124,
      "<DBAF43F0>": "[ML:undisp ](intake of breath)"
    },
    {
      "$id": 32,
      "<8C7DD24D>": "<38229BA9>",
      "<554EE944>": 124,
      "<DBAF43F0>": "All right, that's enough."
    },
    {
      "$id": 33,
      "<8C7DD24D>": "<8B87FA4E>",
      "<554EE944>": 124,
      "<DBAF43F0>": "Whatever the reason, the old man did choose 'em."
    },
    {
      "$id": 34,
      "<8C7DD24D>": "<410AE484>",
      "<554EE944>": 124,
      "<DBAF43F0>": "To be fair, they have gone against\nquite a few Moebius already."
    },
    {
      "$id": 35,
      "<8C7DD24D>": "<FE58F282>",
      "<554EE944>": 124,
      "<DBAF43F0>": "They're the real thing all right."
    },
    {
      "$id": 36,
      "<8C7DD24D>": "<7C55FFCD>",
      "<554EE944>": 124,
      "<DBAF43F0>": "You heard Shania's reports."
    },
    {
      "$id": 37,
      "<8C7DD24D>": "<A8D7BD0D>",
      "<554EE944>": 124,
      "<DBAF43F0>": "What reports?"
    },
    {
      "$id": 38,
      "<8C7DD24D>": "<7BF40CE7>",
      "<554EE944>": 124,
      "<DBAF43F0>": "I had her monitor your actions\nwith extreme scrutiny."
    },
    {
      "$id": 39,
      "<8C7DD24D>": "<FB97C7DD>",
      "<554EE944>": 124,
      "<DBAF43F0>": "All the way from the valley."
    },
    {
      "$id": 40,
      "<8C7DD24D>": "<BE889B98>",
      "<554EE944>": 124,
      "<DBAF43F0>": "Huh?"
    },
    {
      "$id": 41,
      "<8C7DD24D>": "<17BF559C>",
      "<554EE944>": 124,
      "<DBAF43F0>": "Since way back then...?"
    },
    {
      "$id": 42,
      "<8C7DD24D>": "<24F520FB>",
      "<554EE944>": 124,
      "<DBAF43F0>": "Heh."
    },
    {
      "$id": 43,
      "<8C7DD24D>": "<1CCE7DAE>",
      "<554EE944>": 124,
      "<DBAF43F0>": "Together, we are united in our cause."
    },
    {
      "$id": 44,
      "<8C7DD24D>": "<63A8A979>",
      "<554EE944>": 124,
      "<DBAF43F0>": "Ms. Vandham..."
    },
    {
      "$id": 45,
      "<8C7DD24D>": "<3DA66B5F>",
      "<554EE944>": 124,
      "<DBAF43F0>": "Uh... All right then."
    },
    {
      "$id": 46,
      "<8C7DD24D>": "<1B8ADC92>",
      "<554EE944>": 124,
      "<DBAF43F0>": "[ML:undisp ](breath, slightly awed)"
    },
    {
      "$id": 47,
      "<8C7DD24D>": "<305ED4A8>",
      "<554EE944>": 124,
      "<DBAF43F0>": "Please, it's not their fault."
    },
    {
      "$id": 48,
      "<8C7DD24D>": "<8E3D6667>",
      "<554EE944>": 124,
      "<DBAF43F0>": "They're not a bad lot, really."
    },
    {
      "$id": 49,
      "<8C7DD24D>": "<76A3B20A>",
      "<554EE944>": 124,
      "<DBAF43F0>": "That's easy for you to say..."
    },
    {
      "$id": 50,
      "<8C7DD24D>": "<5A9BFB6E>",
      "<554EE944>": 124,
      "<DBAF43F0>": "Well, that was awkward as all ash."
    }
  ]
}