{
  "schema": [
    {
      "name": "<8C7DD24D>",
      "type": 9
    },
    {
      "name": "<ACF3531A>",
      "type": 7
    },
    {
      "name": "<9EE99B1E>",
      "type": 2
    },
    {
      "name": "<2B51649C>",
      "type": 3
    },
    {
      "name": "<C1A03E98>",
      "type": 3
    },
    {
      "name": "<554EE944>",
      "type": 2
    },
    {
      "name": "<DBAF43F0>",
      "type": 7
    }
  ],
  "rows": [
    {
      "$id": 1,
      "<8C7DD24D>": "<F9DBF4CA>",
      "<ACF3531A>": "L",
      "<9EE99B1E>": 33024,
      "<2B51649C>": 16513,
      "<C1A03E98>": 1072,
      "<554EE944>": 126,
      "<DBAF43F0>": "Do you have time now, Koto?"
    },
    {
      "$id": 2,
      "<8C7DD24D>": "<C5AC566D>",
      "<ACF3531A>": "fd1",
      "<9EE99B1E>": 33024,
      "<2B51649C>": 16513,
      "<C1A03E98>": 1072,
      "<554EE944>": 126,
      "<DBAF43F0>": "Yes, what is it?"
    },
    {
      "$id": 3,
      "<8C7DD24D>": "<277F6CE9>",
      "<ACF3531A>": "3",
      "<9EE99B1E>": 33024,
      "<2B51649C>": 16513,
      "<C1A03E98>": 1072,
      "<554EE944>": 126,
      "<DBAF43F0>": "I heard you're good at making\naccessories and came to see."
    },
    {
      "$id": 4,
      "<8C7DD24D>": "<E4578A8A>",
      "<ACF3531A>": "fd1",
      "<9EE99B1E>": 33096,
      "<2B51649C>": 16513,
      "<C1A03E98>": 1072,
      "<554EE944>": 126,
      "<DBAF43F0>": "Oh, um...... I don't know if I'm\ngood, but I do like making them."
    },
    {
      "$id": 5,
      "<8C7DD24D>": "<3954A28E>",
      "<ACF3531A>": "Xd1",
      "<9EE99B1E>": 33024,
      "<2B51649C>": 16513,
      "<C1A03E98>": 1072,
      "<554EE944>": 126,
      "<DBAF43F0>": "Don't be modest. You were praised for\nbeing cute in Gamma, weren't you?"
    },
    {
      "$id": 6,
      "<8C7DD24D>": "<6A2F537D>",
      "<ACF3531A>": "fd1",
      "<9EE99B1E>": 33144,
      "<2B51649C>": 16513,
      "<C1A03E98>": 1072,
      "<554EE944>": 126,
      "<DBAF43F0>": "Ugh, well...... but you don't usually\nsay those things yourself, do you?"
    },
    {
      "$id": 7,
      "<8C7DD24D>": "<A067DBE0>",
      "<ACF3531A>": "2",
      "<9EE99B1E>": 33056,
      "<2B51649C>": 16513,
      "<C1A03E98>": 1072,
      "<554EE944>": 126,
      "<DBAF43F0>": "But that's amazing, isn't it? I\nthink you can be more proud."
    },
    {
      "$id": 8,
      "<8C7DD24D>": "<E57300F9>",
      "<ACF3531A>": "fd1",
      "<9EE99B1E>": 33168,
      "<2B51649C>": 16513,
      "<C1A03E98>": 1072,
      "<554EE944>": 126,
      "<DBAF43F0>": "Yes...... I suppose so."
    },
    {
      "$id": 9,
      "<8C7DD24D>": "<93FA32DE>",
      "<ACF3531A>": "Xd1",
      "<9EE99B1E>": 33024,
      "<2B51649C>": 16513,
      "<C1A03E98>": 1072,
      "<554EE944>": 126,
      "<DBAF43F0>": "Well, you've come at a good time.\nI have something to ask you."
    },
    {
      "$id": 10,
      "<8C7DD24D>": "<B90A30AE>",
      "<ACF3531A>": "5",
      "<9EE99B1E>": 33024,
      "<2B51649C>": 16513,
      "<C1A03E98>": 1072,
      "<554EE944>": 126,
      "<DBAF43F0>": "Huh? What is it?"
    },
    {
      "$id": 11,
      "<8C7DD24D>": "<C4262D9C>",
      "<ACF3531A>": "Xd1",
      "<9EE99B1E>": 33024,
      "<2B51649C>": 16513,
      "<C1A03E98>": 1072,
      "<554EE944>": 126,
      "<DBAF43F0>": "Koto here says she wants to study\nmore about accessory making."
    },
    {
      "$id": 12,
      "<8C7DD24D>": "<0927DFFA>",
      "<ACF3531A>": "fd1",
      "<9EE99B1E>": 33144,
      "<2B51649C>": 16513,
      "<C1A03E98>": 1072,
      "<554EE944>": 126,
      "<DBAF43F0>": "Hey......!"
    },
    {
      "$id": 13,
      "<8C7DD24D>": "<B649DC05>",
      "<ACF3531A>": "Xd1",
      "<9EE99B1E>": 33024,
      "<2B51649C>": 16513,
      "<C1A03E98>": 1072,
      "<554EE944>": 126,
      "<DBAF43F0>": "She's a bit shy, so she couldn't\nbring herself to say it."
    },
    {
      "$id": 14,
      "<8C7DD24D>": "<41DDB38C>",
      "<ACF3531A>": "Xd1",
      "<9EE99B1E>": 33024,
      "<2B51649C>": 16513,
      "<C1A03E98>": 1072,
      "<554EE944>": 126,
      "<DBAF43F0>": "So I'd like you all to bring\nher various accessories."
    },
    {
      "$id": 15,
      "<8C7DD24D>": "<B6476F2F>",
      "<ACF3531A>": "L",
      "<9EE99B1E>": 33024,
      "<2B51649C>": 16513,
      "<C1A03E98>": 1072,
      "<554EE944>": 126,
      "<DBAF43F0>": "Is that so?"
    },
    {
      "$id": 16,
      "<8C7DD24D>": "<9C80BB3F>",
      "<ACF3531A>": "fd1",
      "<9EE99B1E>": 33064,
      "<2B51649C>": 16513,
      "<C1A03E98>": 1072,
      "<554EE944>": 126,
      "<DBAF43F0>": "Well...... yes...... There are still\nso many things I haven't seen......"
    },
    {
      "$id": 17,
      "<8C7DD24D>": "<EB358C6E>",
      "<ACF3531A>": "fd1",
      "<9EE99B1E>": 33064,
      "<2B51649C>": 16513,
      "<C1A03E98>": 1072,
      "<554EE944>": 126,
      "<DBAF43F0>": "But it's just something I want to do......\nI don't want to cause trouble for the\ncolony by just doing what I like."
    },
    {
      "$id": 18,
      "<8C7DD24D>": "<9425934D>",
      "<ACF3531A>": "4",
      "<9EE99B1E>": 33024,
      "<2B51649C>": 16513,
      "<C1A03E98>": 1072,
      "<554EE944>": 126,
      "<DBAF43F0>": "If you're thinking about the colony's\ndevelopment, I don't think having\nsuch a skill is a bad thing."
    },
    {
      "$id": 19,
      "<8C7DD24D>": "<FA843712>",
      "<ACF3531A>": "L",
      "<9EE99B1E>": 33024,
      "<2B51649C>": 16513,
      "<C1A03E98>": 1072,
      "<554EE944>": 126,
      "<DBAF43F0>": "What do you mean, Taion-san?"
    },
    {
      "$id": 20,
      "<8C7DD24D>": "<A1095DA9>",
      "<ACF3531A>": "4",
      "<9EE99B1E>": 33024,
      "<2B51649C>": 16513,
      "<C1A03E98>": 1072,
      "<554EE944>": 126,
      "<DBAF43F0>": "You can make accessories and\nsell them at other colonies."
    },
    {
      "$id": 21,
      "<8C7DD24D>": "<D12764A2>",
      "<ACF3531A>": "4",
      "<9EE99B1E>": 33024,
      "<2B51649C>": 16513,
      "<C1A03E98>": 1072,
      "<554EE944>": 126,
      "<DBAF43F0>": "There are not a few people\nwho would want such things."
    },
    {
      "$id": 22,
      "<8C7DD24D>": "<4A4143EC>",
      "<ACF3531A>": "L",
      "<9EE99B1E>": 33064,
      "<2B51649C>": 16513,
      "<C1A03E98>": 1072,
      "<554EE944>": 126,
      "<DBAF43F0>": "I see...... That might be\na very good suggestion."
    },
    {
      "$id": 23,
      "<8C7DD24D>": "<DD2AE031>",
      "<ACF3531A>": "L",
      "<9EE99B1E>": 33024,
      "<2B51649C>": 16513,
      "<C1A03E98>": 1072,
      "<554EE944>": 126,
      "<DBAF43F0>": "What do you think, Koto? Your skill\nmight be able to help the colony."
    },
    {
      "$id": 24,
      "<8C7DD24D>": "<82BB3C3D>",
      "<ACF3531A>": "fd1",
      "<9EE99B1E>": 33064,
      "<2B51649C>": 16513,
      "<C1A03E98>": 1072,
      "<554EE944>": 126,
      "<DBAF43F0>": "Yes...... I'll try my best."
    },
    {
      "$id": 25,
      "<8C7DD24D>": "<3F4E78EC>",
      "<ACF3531A>": "fd1",
      "<9EE99B1E>": 33024,
      "<2B51649C>": 16513,
      "<C1A03E98>": 1072,
      "<554EE944>": 126,
      "<DBAF43F0>": "For that...... I really would\nlike to see other accessories."
    },
    {
      "$id": 26,
      "<8C7DD24D>": "<F320E9ED>",
      "<ACF3531A>": "fd1",
      "<9EE99B1E>": 33024,
      "<2B51649C>": 16513,
      "<C1A03E98>": 1072,
      "<554EE944>": 126,
      "<DBAF43F0>": "I think I can make\nbetter things if I do."
    },
    {
      "$id": 27,
      "<8C7DD24D>": "<4A986149>",
      "<ACF3531A>": "1",
      "<9EE99B1E>": 33024,
      "<2B51649C>": 16513,
      "<C1A03E98>": 1072,
      "<554EE944>": 126,
      "<DBAF43F0>": "Then we'll bring them to you."
    },
    {
      "$id": 28,
      "<8C7DD24D>": "<F90EC94F>",
      "<ACF3531A>": "fd1",
      "<9EE99B1E>": 33152,
      "<2B51649C>": 16513,
      "<C1A03E98>": 1072,
      "<554EE944>": 126,
      "<DBAF43F0>": "Thank you! I'd be happy if you\ncould bring as many as possible."
    },
    {
      "$id": 29,
      "<8C7DD24D>": "<4F05874E>",
      "<ACF3531A>": "5",
      "<9EE99B1E>": 33024,
      "<2B51649C>": 16513,
      "<C1A03E98>": 1072,
      "<554EE944>": 126,
      "<DBAF43F0>": "Alright! Let's go and get some!"
    }
  ]
}