{
  "schema": [
    {
      "name": "<8C7DD24D>",
      "type": 9
    },
    {
      "name": "<ACF3531A>",
      "type": 7
    },
    {
      "name": "<9EE99B1E>",
      "type": 2
    },
    {
      "name": "<2B51649C>",
      "type": 3
    },
    {
      "name": "<C1A03E98>",
      "type": 3
    },
    {
      "name": "<554EE944>",
      "type": 2
    },
    {
      "name": "<DBAF43F0>",
      "type": 7
    }
  ],
  "rows": [
    {
      "$id": 1,
      "<8C7DD24D>": "<F90D56CA>",
      "<ACF3531A>": "5",
      "<9EE99B1E>": 33024,
      "<2B51649C>": 16513,
      "<C1A03E98>": 1072,
      "<554EE944>": 126,
      "<DBAF43F0>": "That hammer…… I wasn't\nmistaken after all."
    },
    {
      "$id": 2,
      "<8C7DD24D>": "<1282AFB5>",
      "<ACF3531A>": "5",
      "<9EE99B1E>": 33024,
      "<2B51649C>": 16513,
      "<C1A03E98>": 1072,
      "<554EE944>": 126,
      "<DBAF43F0>": "Hey, you can hear me, can't you? There's\nsomething I'd like to ask of you……"
    },
    {
      "$id": 3,
      "<8C7DD24D>": "<34D016BF>",
      "<ACF3531A>": "ta1",
      "<9EE99B1E>": 33024,
      "<2B51649C>": 16513,
      "<C1A03E98>": 1072,
      "<554EE944>": 126,
      "<DBAF43F0>": "……Please go home mo. I will not\nuse the hammer anymore mo."
    },
    {
      "$id": 4,
      "<8C7DD24D>": "<B57C50AC>",
      "<ACF3531A>": "ta1",
      "<9EE99B1E>": 33024,
      "<2B51649C>": 16513,
      "<C1A03E98>": 1072,
      "<554EE944>": 126,
      "<DBAF43F0>": "Fixing...have no more meaning..."
    },
    {
      "$id": 5,
      "<8C7DD24D>": "<158147AB>",
      "<ACF3531A>": "5",
      "<9EE99B1E>": 33024,
      "<2B51649C>": 16513,
      "<C1A03E98>": 1072,
      "<554EE944>": 126,
      "<DBAF43F0>": "Huh? What do you mean by that……"
    },
    {
      "$id": 6,
      "<8C7DD24D>": "<19E7CFA1>",
      "<ACF3531A>": "ta1",
      "<9EE99B1E>": 33024,
      "<2B51649C>": 16513,
      "<C1A03E98>": 1072,
      "<554EE944>": 126,
      "<DBAF43F0>": "…………"
    },
    {
      "$id": 7,
      "<8C7DD24D>": "<C0AFB70F>",
      "<ACF3531A>": "5",
      "<9EE99B1E>": 33024,
      "<2B51649C>": 16513,
      "<C1A03E98>": 1072,
      "<554EE944>": 126,
      "<DBAF43F0>": "……Tch. Silent treatment, huh."
    },
    {
      "$id": 8,
      "<8C7DD24D>": "<D824CC3B>",
      "<ACF3531A>": "6",
      "<9EE99B1E>": 33024,
      "<2B51649C>": 16513,
      "<C1A03E98>": 1072,
      "<554EE944>": 126,
      "<DBAF43F0>": "I wonder if there's a way\nto get him to talk……?"
    },
    {
      "$id": 9,
      "<8C7DD24D>": "<E3D1DF20>",
      "<ACF3531A>": "H",
      "<9EE99B1E>": 33024,
      "<2B51649C>": 16513,
      "<C1A03E98>": 1072,
      "<554EE944>": 126,
      "<DBAF43F0>": "……Master?"
    },
    {
      "$id": 10,
      "<8C7DD24D>": "<855947CF>",
      "<ACF3531A>": "ta1",
      "<9EE99B1E>": 33024,
      "<2B51649C>": 16513,
      "<C1A03E98>": 1072,
      "<554EE944>": 126,
      "<DBAF43F0>": "……!"
    },
    {
      "$id": 11,
      "<8C7DD24D>": "<D77142A4>",
      "<ACF3531A>": "ta1",
      "<9EE99B1E>": 33024,
      "<2B51649C>": 16513,
      "<C1A03E98>": 1072,
      "<554EE944>": 126,
      "<DBAF43F0>": "Rudi……?"
    },
    {
      "$id": 12,
      "<8C7DD24D>": "<69DF5C27>",
      "<ACF3531A>": "H",
      "<9EE99B1E>": 33024,
      "<2B51649C>": 16513,
      "<C1A03E98>": 1072,
      "<554EE944>": 126,
      "<DBAF43F0>": "It really is you, Master!"
    },
    {
      "$id": 13,
      "<8C7DD24D>": "<AE614D70>",
      "<ACF3531A>": "H",
      "<9EE99B1E>": 33024,
      "<2B51649C>": 16513,
      "<C1A03E98>": 1072,
      "<554EE944>": 126,
      "<DBAF43F0>": "What are you doing in a place\nlike this? Are you trapped?"
    },
    {
      "$id": 14,
      "<8C7DD24D>": "<6ABFCA02>",
      "<ACF3531A>": "ta1",
      "<9EE99B1E>": 33024,
      "<2B51649C>": 16513,
      "<C1A03E98>": 1072,
      "<554EE944>": 126,
      "<DBAF43F0>": "Rudi…… Tobari is tired mo."
    },
    {
      "$id": 15,
      "<8C7DD24D>": "<061E9217>",
      "<ACF3531A>": "ta1",
      "<9EE99B1E>": 33024,
      "<2B51649C>": 16513,
      "<C1A03E98>": 1072,
      "<554EE944>": 126,
      "<DBAF43F0>": "Building and fixing, it was\nall meaningless mo. They break,\nthey damage, they steal……"
    },
    {
      "$id": 16,
      "<8C7DD24D>": "<A9170439>",
      "<ACF3531A>": "ta1",
      "<9EE99B1E>": 33024,
      "<2B51649C>": 16513,
      "<C1A03E98>": 1072,
      "<554EE944>": 126,
      "<DBAF43F0>": "The beings on Aionios think only\nof fighting mo. That is why……"
    },
    {
      "$id": 17,
      "<8C7DD24D>": "<565A8A5C>",
      "<ACF3531A>": "H",
      "<9EE99B1E>": 33024,
      "<2B51649C>": 16513,
      "<C1A03E98>": 1072,
      "<554EE944>": 126,
      "<DBAF43F0>": "……Do you think that way about me too?\nDid you feel that way \"back then\"?"
    },
    {
      "$id": 18,
      "<8C7DD24D>": "<149DC7B4>",
      "<ACF3531A>": "ta1",
      "<9EE99B1E>": 33024,
      "<2B51649C>": 16513,
      "<C1A03E98>": 1072,
      "<554EE944>": 126,
      "<DBAF43F0>": "Mo mo……?"
    },
    {
      "$id": 19,
      "<8C7DD24D>": "<89DB5CEA>",
      "<ACF3531A>": "H",
      "<9EE99B1E>": 33024,
      "<2B51649C>": 16513,
      "<C1A03E98>": 1072,
      "<554EE944>": 126,
      "<DBAF43F0>": "\"Make yourself an ally. Never\nmake yourself an enemy\"……"
    },
    {
      "$id": 20,
      "<8C7DD24D>": "<7019E156>",
      "<ACF3531A>": "H",
      "<9EE99B1E>": 33024,
      "<2B51649C>": 16513,
      "<C1A03E98>": 1072,
      "<554EE944>": 126,
      "<DBAF43F0>": "Those are your words, Master.\nAlong with this gauntlet, they\nhave always supported me."
    },
    {
      "$id": 21,
      "<8C7DD24D>": "<16C94451>",
      "<ACF3531A>": "H",
      "<9EE99B1E>": 33024,
      "<2B51649C>": 16513,
      "<C1A03E98>": 1072,
      "<554EE944>": 126,
      "<DBAF43F0>": "……Now it is my turn to support you."
    },
    {
      "$id": 22,
      "<8C7DD24D>": "<2E8923F2>",
      "<ACF3531A>": "ta1",
      "<9EE99B1E>": 33024,
      "<2B51649C>": 16513,
      "<C1A03E98>": 1072,
      "<554EE944>": 126,
      "<DBAF43F0>": "……Rudi……"
    },
    {
      "$id": 23,
      "<8C7DD24D>": "<4601F3B4>",
      "<ACF3531A>": "H",
      "<9EE99B1E>": 33024,
      "<2B51649C>": 16513,
      "<C1A03E98>": 1072,
      "<554EE944>": 126,
      "<DBAF43F0>": "For now, let's get out of here!"
    },
    {
      "$id": 24,
      "<8C7DD24D>": "<C0F9C6FC>",
      "<ACF3531A>": "H",
      "<9EE99B1E>": 33024,
      "<2B51649C>": 16513,
      "<C1A03E98>": 1072,
      "<554EE944>": 126,
      "<DBAF43F0>": "You seem so deflated,\nMaster, I'm worried……"
    },
    {
      "$id": 25,
      "<8C7DD24D>": "<7EA1A551>",
      "<ACF3531A>": "ta1",
      "<9EE99B1E>": 33024,
      "<2B51649C>": 16513,
      "<C1A03E98>": 1072,
      "<554EE944>": 126,
      "<DBAF43F0>": "…………"
    },
    {
      "$id": 26,
      "<8C7DD24D>": "<03AD4F6F>",
      "<ACF3531A>": "ta1",
      "<9EE99B1E>": 33024,
      "<2B51649C>": 16513,
      "<C1A03E98>": 1072,
      "<554EE944>": 126,
      "<DBAF43F0>": "Is there something you want\nTobari to build mo? Let us move\nto the workshop at once mo."
    },
    {
      "$id": 27,
      "<8C7DD24D>": "<663065A8>",
      "<ACF3531A>": "H",
      "<9EE99B1E>": 33024,
      "<2B51649C>": 16513,
      "<C1A03E98>": 1072,
      "<554EE944>": 126,
      "<DBAF43F0>": "Huh!? But Master, you\nsaid you were tired……"
    },
    {
      "$id": 28,
      "<8C7DD24D>": "<2C6D9F2E>",
      "<ACF3531A>": "ta1",
      "<9EE99B1E>": 33024,
      "<2B51649C>": 16513,
      "<C1A03E98>": 1072,
      "<554EE944>": 126,
      "<DBAF43F0>": "I cannot just stand by and watch\nwhile my apprentice is fighting mo."
    },
    {
      "$id": 29,
      "<8C7DD24D>": "<EF517789>",
      "<ACF3531A>": "ta1",
      "<9EE99B1E>": 33024,
      "<2B51649C>": 16513,
      "<C1A03E98>": 1072,
      "<554EE944>": 126,
      "<DBAF43F0>": "If I do…… Tobari will make\nan enemy of himself mo."
    },
    {
      "$id": 30,
      "<8C7DD24D>": "<DE20BE43>",
      "<ACF3531A>": "H",
      "<9EE99B1E>": 33024,
      "<2B51649C>": 16513,
      "<C1A03E98>": 1072,
      "<554EE944>": 126,
      "<DBAF43F0>": "……! Master……!"
    },
    {
      "$id": 31,
      "<8C7DD24D>": "<CB7D6168>",
      "<ACF3531A>": "6",
      "<9EE99B1E>": 33024,
      "<2B51649C>": 16513,
      "<C1A03E98>": 1072,
      "<554EE944>": 126,
      "<DBAF43F0>": "It's at these coordinates…… Do you\nthink you can get there by yourself?"
    },
    {
      "$id": 32,
      "<8C7DD24D>": "<BDA729A7>",
      "<ACF3531A>": "ta1",
      "<9EE99B1E>": 33024,
      "<2B51649C>": 16513,
      "<C1A03E98>": 1072,
      "<554EE944>": 126,
      "<DBAF43F0>": "Leave it to me mo."
    },
    {
      "$id": 33,
      "<8C7DD24D>": "<AE5D83F9>",
      "<ACF3531A>": "ta1",
      "<9EE99B1E>": 33024,
      "<2B51649C>": 16513,
      "<C1A03E98>": 1072,
      "<554EE944>": 126,
      "<DBAF43F0>": "It is 1000 years too early for\nRudi to be supporting Tobari mo."
    },
    {
      "$id": 34,
      "<8C7DD24D>": "<BCC16E07>",
      "<ACF3531A>": "ta1",
      "<9EE99B1E>": 33024,
      "<2B51649C>": 16513,
      "<C1A03E98>": 1072,
      "<554EE944>": 126,
      "<DBAF43F0>": "Witness…… the work of a master mo!"
    },
    {
      "$id": 35,
      "<8C7DD24D>": "<69A54524>",
      "<ACF3531A>": "H",
      "<9EE99B1E>": 33024,
      "<2B51649C>": 16513,
      "<C1A03E98>": 1072,
      "<554EE944>": 126,
      "<DBAF43F0>": "Yes! I'm counting on\nyou again, Master!!"
    }
  ]
}