{
  "schema": [
    {
      "name": "<8C7DD24D>",
      "type": 9
    },
    {
      "name": "<554EE944>",
      "type": 2
    },
    {
      "name": "<DBAF43F0>",
      "type": 7
    }
  ],
  "rows": [
    {
      "$id": 1,
      "<8C7DD24D>": "<0CAA3FD0>",
      "<554EE944>": 124,
      "<DBAF43F0>": "15 years ago feels like a dream now."
    },
    {
      "$id": 2,
      "<8C7DD24D>": "<56B9DECB>",
      "<554EE944>": 124,
      "<DBAF43F0>": "Like it was an eternity away..."
    },
    {
      "$id": 3,
      "<8C7DD24D>": "<D4B8F317>",
      "<554EE944>": 124,
      "<DBAF43F0>": "You might never have to use those again."
    },
    {
      "$id": 4,
      "<8C7DD24D>": "<2176433E>",
      "<554EE944>": 124,
      "<DBAF43F0>": "Now wouldn't that be amazing?"
    },
    {
      "$id": 5,
      "<8C7DD24D>": "<5435D4E0>",
      "<554EE944>": 124,
      "<DBAF43F0>": "The Queen of Keves, though... She's still not free."
    },
    {
      "$id": 6,
      "<8C7DD24D>": "<A6992F6C>",
      "<554EE944>": 124,
      "<DBAF43F0>": "What, you think our fight's still not over?"
    },
    {
      "$id": 7,
      "<8C7DD24D>": "<186A0DA4>",
      "<554EE944>": 124,
      "<DBAF43F0>": "Can't things stay like this?"
    },
    {
      "$id": 8,
      "<8C7DD24D>": "<62061553>",
      "<554EE944>": 124,
      "<DBAF43F0>": "The soldiers, they're still fighting."
    },
    {
      "$id": 9,
      "<8C7DD24D>": "<3F62FF99>",
      "<554EE944>": 124,
      "<DBAF43F0>": "Right this moment."
    },
    {
      "$id": 10,
      "<8C7DD24D>": "<7DEB4683>",
      "<554EE944>": 124,
      "<DBAF43F0>": "Personally..."
    },
    {
      "$id": 11,
      "<8C7DD24D>": "<488B80A0>",
      "<554EE944>": 124,
      "<DBAF43F0>": "If things could just stay this way... I'd be happy."
    },
    {
      "$id": 12,
      "<8C7DD24D>": "<76F56951>",
      "<554EE944>": 124,
      "<DBAF43F0>": "You serious?"
    },
    {
      "$id": 13,
      "<8C7DD24D>": "<8C2E23F4>",
      "<554EE944>": 124,
      "<DBAF43F0>": "If Grandad could hear you, he'd lay you out flat."
    },
    {
      "$id": 14,
      "<8C7DD24D>": "<E9E6F9DA>",
      "<554EE944>": 124,
      "<DBAF43F0>": "Yeah, I know what he'd say. \"The soldiers\nare the roots from which we grew.\""
    },
    {
      "$id": 15,
      "<8C7DD24D>": "<C080C3D1>",
      "<554EE944>": 124,
      "<DBAF43F0>": "But still...we are who we are, right?"
    },
    {
      "$id": 16,
      "<8C7DD24D>": "<C149CEDF>",
      "<554EE944>": 124,
      "<DBAF43F0>": "And them and the Moebius, they're a whole different story."
    },
    {
      "$id": 17,
      "<8C7DD24D>": "<8C8FA700>",
      "<554EE944>": 124,
      "<DBAF43F0>": "No reason we can't coexist..."
    },
    {
      "$id": 18,
      "<8C7DD24D>": "<CA76738C>",
      "<554EE944>": 124,
      "<DBAF43F0>": "Nah, don't gimme that. Come on!"
    },
    {
      "$id": 19,
      "<8C7DD24D>": "<4A7BDE8D>",
      "<554EE944>": 124,
      "<DBAF43F0>": "There's no need to fight if we just\nstay out of each other's way."
    },
    {
      "$id": 20,
      "<8C7DD24D>": "<8E9CAF93>",
      "<554EE944>": 124,
      "<DBAF43F0>": "It's worked out fine for the past 15 years."
    },
    {
      "$id": 21,
      "<8C7DD24D>": "<E0D64DDF>",
      "<554EE944>": 124,
      "<DBAF43F0>": "I guess for you...\nit's all or nothing, huh?"
    },
    {
      "$id": 22,
      "<8C7DD24D>": "<6BBDC0F6>",
      "<554EE944>": 124,
      "<DBAF43F0>": "Huh?"
    },
    {
      "$id": 23,
      "<8C7DD24D>": "<C6BA4128>",
      "<554EE944>": 124,
      "<DBAF43F0>": "Those children are everything to me, you know."
    },
    {
      "$id": 24,
      "<8C7DD24D>": "<54B2CB52>",
      "<554EE944>": 124,
      "<DBAF43F0>": "...What choice have I got?"
    },
    {
      "$id": 25,
      "<8C7DD24D>": "<E7E32F5B>",
      "<554EE944>": 124,
      "<DBAF43F0>": "[ML:undisp ](uncertain murmur)"
    }
  ]
}