{
  "schema": [
    {
      "name": "<8C7DD24D>",
      "type": 9
    },
    {
      "name": "<ACF3531A>",
      "type": 7
    },
    {
      "name": "<9EE99B1E>",
      "type": 2
    },
    {
      "name": "<2B51649C>",
      "type": 3
    },
    {
      "name": "<C1A03E98>",
      "type": 3
    },
    {
      "name": "<554EE944>",
      "type": 2
    },
    {
      "name": "<DBAF43F0>",
      "type": 7
    }
  ],
  "rows": [
    {
      "$id": 1,
      "<8C7DD24D>": "<5F048BC7>",
      "<ACF3531A>": "gW1",
      "<9EE99B1E>": 33024,
      "<2B51649C>": 16513,
      "<C1A03E98>": 1072,
      "<554EE944>": 126,
      "<DBAF43F0>": "The final battle... This might just be\nmy last big job as Acting Commander."
    },
    {
      "$id": 2,
      "<8C7DD24D>": "<5CF22689>",
      "<ACF3531A>": "gW1",
      "<9EE99B1E>": 33024,
      "<2B51649C>": 16513,
      "<C1A03E98>": 1072,
      "<554EE944>": 126,
      "<DBAF43F0>": "Whoa, let me be clear, I'm not planning to\ndie. If I kicked the bucket here, I'd never\nbe able to face Commander Ethel again!"
    },
    {
      "$id": 3,
      "<8C7DD24D>": "<552FBDBE>",
      "<ACF3531A>": "5",
      "<9EE99B1E>": 33024,
      "<2B51649C>": 16513,
      "<C1A03E98>": 1072,
      "<554EE944>": 126,
      "<DBAF43F0>": "Don't you worry. A guy like you is\nthe type who's too stubborn to die."
    },
    {
      "$id": 4,
      "<8C7DD24D>": "<93267555>",
      "<ACF3531A>": "gW1",
      "<9EE99B1E>": 33024,
      "<2B51649C>": 16513,
      "<C1A03E98>": 1072,
      "<554EE944>": 126,
      "<DBAF43F0>": "You bet! ...Wait, that\nwas a compliment, right?"
    }
  ]
}