{
  "schema": [
    {
      "name": "<8C7DD24D>",
      "type": 9
    },
    {
      "name": "<ACF3531A>",
      "type": 7
    },
    {
      "name": "<9EE99B1E>",
      "type": 2
    },
    {
      "name": "<2B51649C>",
      "type": 3
    },
    {
      "name": "<C1A03E98>",
      "type": 3
    },
    {
      "name": "<554EE944>",
      "type": 2
    },
    {
      "name": "<DBAF43F0>",
      "type": 7
    }
  ],
  "rows": [
    {
      "$id": 1,
      "<8C7DD24D>": "<B1FEBB86>",
      "<ACF3531A>": "",
      "<9EE99B1E>": 33024,
      "<2B51649C>": 16513,
      "<C1A03E98>": 1072,
      "<554EE944>": 124,
      "<DBAF43F0>": "Aya,"
    },
    {
      "$id": 2,
      "<8C7DD24D>": "<81558AD6>",
      "<ACF3531A>": "",
      "<9EE99B1E>": 33024,
      "<2B51649C>": 16513,
      "<C1A03E98>": 1072,
      "<554EE944>": 124,
      "<DBAF43F0>": "everyone..."
    },
    {
      "$id": 3,
      "<8C7DD24D>": "<D0E1AAA6>",
      "<ACF3531A>": "",
      "<9EE99B1E>": 33024,
      "<2B51649C>": 16513,
      "<C1A03E98>": 1072,
      "<554EE944>": 124,
      "<DBAF43F0>": "I've got something to say to you all."
    },
    {
      "$id": 4,
      "<8C7DD24D>": "<727C594C>",
      "<ACF3531A>": "",
      "<9EE99B1E>": 33024,
      "<2B51649C>": 16513,
      "<C1A03E98>": 1072,
      "<554EE944>": 124,
      "<DBAF43F0>": "I'm sorry for the worries."
    },
    {
      "$id": 5,
      "<8C7DD24D>": "<198844EC>",
      "<ACF3531A>": "",
      "<9EE99B1E>": 33024,
      "<2B51649C>": 16513,
      "<C1A03E98>": 1072,
      "<554EE944>": 124,
      "<DBAF43F0>": "I wasn't sure... If I should tell you..."
    },
    {
      "$id": 6,
      "<8C7DD24D>": "<C190ABB9>",
      "<ACF3531A>": "",
      "<9EE99B1E>": 33024,
      "<2B51649C>": 16513,
      "<C1A03E98>": 1072,
      "<554EE944>": 124,
      "<DBAF43F0>": "About Ichika..."
    },
    {
      "$id": 7,
      "<8C7DD24D>": "<2D22709F>",
      "<ACF3531A>": "",
      "<9EE99B1E>": 33024,
      "<2B51649C>": 16513,
      "<C1A03E98>": 1072,
      "<554EE944>": 124,
      "<DBAF43F0>": "Did something...happen?"
    },
    {
      "$id": 8,
      "<8C7DD24D>": "<D5007D28>",
      "<ACF3531A>": "",
      "<9EE99B1E>": 33024,
      "<2B51649C>": 16513,
      "<C1A03E98>": 1072,
      "<554EE944>": 124,
      "<DBAF43F0>": "We thought you were just out of sorts.\nThat you were trying to get over her death."
    },
    {
      "$id": 9,
      "<8C7DD24D>": "<BFE08301>",
      "<ACF3531A>": "",
      "<9EE99B1E>": 33024,
      "<2B51649C>": 16513,
      "<C1A03E98>": 1072,
      "<554EE944>": 124,
      "<DBAF43F0>": "There's more to it than that, then?"
    },
    {
      "$id": 10,
      "<8C7DD24D>": "<A8C503EF>",
      "<ACF3531A>": "",
      "<9EE99B1E>": 33024,
      "<2B51649C>": 16513,
      "<C1A03E98>": 1072,
      "<554EE944>": 124,
      "<DBAF43F0>": "...Yeah."
    },
    {
      "$id": 11,
      "<8C7DD24D>": "<BEF81FB7>",
      "<ACF3531A>": "",
      "<9EE99B1E>": 33024,
      "<2B51649C>": 16513,
      "<C1A03E98>": 1072,
      "<554EE944>": 124,
      "<DBAF43F0>": "I couldn't... I couldn't face it."
    },
    {
      "$id": 12,
      "<8C7DD24D>": "<A58667C4>",
      "<ACF3531A>": "",
      "<9EE99B1E>": 33024,
      "<2B51649C>": 16513,
      "<C1A03E98>": 1072,
      "<554EE944>": 124,
      "<DBAF43F0>": "I just didn't want to see you all hurt."
    },
    {
      "$id": 13,
      "<8C7DD24D>": "<87ECB176>",
      "<ACF3531A>": "",
      "<9EE99B1E>": 33024,
      "<2B51649C>": 16513,
      "<C1A03E98>": 1072,
      "<554EE944>": 124,
      "<DBAF43F0>": "I was only seeing what I wanted to."
    },
    {
      "$id": 14,
      "<8C7DD24D>": "<135C3DC6>",
      "<ACF3531A>": "",
      "<9EE99B1E>": 33024,
      "<2B51649C>": 16513,
      "<C1A03E98>": 1072,
      "<554EE944>": 124,
      "<DBAF43F0>": "I think... I think doing that only hurt you more."
    },
    {
      "$id": 15,
      "<8C7DD24D>": "<95B3342A>",
      "<ACF3531A>": "",
      "<9EE99B1E>": 33024,
      "<2B51649C>": 16513,
      "<C1A03E98>": 1072,
      "<554EE944>": 124,
      "<DBAF43F0>": "Hang on, what's this about?"
    },
    {
      "$id": 16,
      "<8C7DD24D>": "<047DC074>",
      "<ACF3531A>": "",
      "<9EE99B1E>": 33024,
      "<2B51649C>": 16513,
      "<C1A03E98>": 1072,
      "<554EE944>": 124,
      "<DBAF43F0>": "You didn't do anything wrong, Shiro-chan!"
    },
    {
      "$id": 17,
      "<8C7DD24D>": "<064609A0>",
      "<ACF3531A>": "",
      "<9EE99B1E>": 33024,
      "<2B51649C>": 16513,
      "<C1A03E98>": 1072,
      "<554EE944>": 124,
      "<DBAF43F0>": "Ichika was wrong, but she wasn't the only one."
    },
    {
      "$id": 18,
      "<8C7DD24D>": "<FB487A86>",
      "<ACF3531A>": "",
      "<9EE99B1E>": 33024,
      "<2B51649C>": 16513,
      "<C1A03E98>": 1072,
      "<554EE944>": 124,
      "<DBAF43F0>": "It took some time,"
    },
    {
      "$id": 19,
      "<8C7DD24D>": "<00488E3F>",
      "<ACF3531A>": "",
      "<9EE99B1E>": 33024,
      "<2B51649C>": 16513,
      "<C1A03E98>": 1072,
      "<554EE944>": 124,
      "<DBAF43F0>": "but now I know."
    },
    {
      "$id": 20,
      "<8C7DD24D>": "<983DC4E8>",
      "<ACF3531A>": "",
      "<9EE99B1E>": 33024,
      "<2B51649C>": 16513,
      "<C1A03E98>": 1072,
      "<554EE944>": 124,
      "<DBAF43F0>": "I want to...start again."
    },
    {
      "$id": 21,
      "<8C7DD24D>": "<57D64C5F>",
      "<ACF3531A>": "",
      "<9EE99B1E>": 33024,
      "<2B51649C>": 16513,
      "<C1A03E98>": 1072,
      "<554EE944>": 124,
      "<DBAF43F0>": "Work to rebuild it all."
    },
    {
      "$id": 22,
      "<8C7DD24D>": "<547FC46B>",
      "<ACF3531A>": "",
      "<9EE99B1E>": 33024,
      "<2B51649C>": 16513,
      "<C1A03E98>": 1072,
      "<554EE944>": 124,
      "<DBAF43F0>": "I want to come clean. Will you hear my story?"
    },
    {
      "$id": 23,
      "<8C7DD24D>": "<4AF1279F>",
      "<ACF3531A>": "",
      "<9EE99B1E>": 33024,
      "<2B51649C>": 16513,
      "<C1A03E98>": 1072,
      "<554EE944>": 124,
      "<DBAF43F0>": "I'm a lousy commander. Sorry."
    },
    {
      "$id": 24,
      "<8C7DD24D>": "<BEE4E25A>",
      "<ACF3531A>": "",
      "<9EE99B1E>": 33024,
      "<2B51649C>": 16513,
      "<C1A03E98>": 1072,
      "<554EE944>": 124,
      "<DBAF43F0>": "Oh, come off it."
    },
    {
      "$id": 25,
      "<8C7DD24D>": "<1F8E90F7>",
      "<ACF3531A>": "",
      "<9EE99B1E>": 33024,
      "<2B51649C>": 16513,
      "<C1A03E98>": 1072,
      "<554EE944>": 124,
      "<DBAF43F0>": "We're the ones who should be sorry,"
    },
    {
      "$id": 26,
      "<8C7DD24D>": "<5431AEE6>",
      "<ACF3531A>": "",
      "<9EE99B1E>": 33024,
      "<2B51649C>": 16513,
      "<C1A03E98>": 1072,
      "<554EE944>": 124,
      "<DBAF43F0>": "for letting you struggle, alone."
    },
    {
      "$id": 27,
      "<8C7DD24D>": "<063A4508>",
      "<ACF3531A>": "",
      "<9EE99B1E>": 33024,
      "<2B51649C>": 16513,
      "<C1A03E98>": 1072,
      "<554EE944>": 124,
      "<DBAF43F0>": "It might take some time..."
    },
    {
      "$id": 28,
      "<8C7DD24D>": "<228512EB>",
      "<ACF3531A>": "",
      "<9EE99B1E>": 33024,
      "<2B51649C>": 16513,
      "<C1A03E98>": 1072,
      "<554EE944>": 124,
      "<DBAF43F0>": "Is that all right?"
    },
    {
      "$id": 29,
      "<8C7DD24D>": "<8EDC8D0A>",
      "<ACF3531A>": "",
      "<9EE99B1E>": 33024,
      "<2B51649C>": 16513,
      "<C1A03E98>": 1072,
      "<554EE944>": 124,
      "<DBAF43F0>": "Of course!"
    },
    {
      "$id": 30,
      "<8C7DD24D>": "<403D88D2>",
      "<ACF3531A>": "",
      "<9EE99B1E>": 33024,
      "<2B51649C>": 16513,
      "<C1A03E98>": 1072,
      "<554EE944>": 124,
      "<DBAF43F0>": "Shiro-chan!"
    },
    {
      "$id": 31,
      "<8C7DD24D>": "<5D9F8C4C>",
      "<ACF3531A>": "",
      "<9EE99B1E>": 33024,
      "<2B51649C>": 16513,
      "<C1A03E98>": 1072,
      "<554EE944>": 124,
      "<DBAF43F0>": "We'll help you shoulder it!"
    },
    {
      "$id": 32,
      "<8C7DD24D>": "<67696BA2>",
      "<ACF3531A>": "",
      "<9EE99B1E>": 33024,
      "<2B51649C>": 16513,
      "<C1A03E98>": 1072,
      "<554EE944>": 124,
      "<DBAF43F0>": "Of course we will! We all will!"
    },
    {
      "$id": 33,
      "<8C7DD24D>": "<EB501886>",
      "<ACF3531A>": "",
      "<9EE99B1E>": 33024,
      "<2B51649C>": 16513,
      "<C1A03E98>": 1072,
      "<554EE944>": 124,
      "<DBAF43F0>": "Wow. She sure is brave...\nfor such a crybaby."
    },
    {
      "$id": 34,
      "<8C7DD24D>": "<D6EAE8A1>",
      "<ACF3531A>": "",
      "<9EE99B1E>": 33024,
      "<2B51649C>": 16513,
      "<C1A03E98>": 1072,
      "<554EE944>": 124,
      "<DBAF43F0>": "She was afraid of making mistakes, before now...\nDo you think she's over that?"
    },
    {
      "$id": 35,
      "<8C7DD24D>": "<E64D344A>",
      "<ACF3531A>": "",
      "<9EE99B1E>": 33024,
      "<2B51649C>": 16513,
      "<C1A03E98>": 1072,
      "<554EE944>": 124,
      "<DBAF43F0>": "Eh, I doubt it'll be that easy."
    },
    {
      "$id": 36,
      "<8C7DD24D>": "<4E23F495>",
      "<ACF3531A>": "",
      "<9EE99B1E>": 33024,
      "<2B51649C>": 16513,
      "<C1A03E98>": 1072,
      "<554EE944>": 124,
      "<DBAF43F0>": "But, so what if she does?"
    },
    {
      "$id": 37,
      "<8C7DD24D>": "<AB388035>",
      "<ACF3531A>": "",
      "<9EE99B1E>": 33024,
      "<2B51649C>": 16513,
      "<C1A03E98>": 1072,
      "<554EE944>": 124,
      "<DBAF43F0>": "At least now, she knows she won't\nbe staying wrong for long."
    },
    {
      "$id": 38,
      "<8C7DD24D>": "<3B611CB5>",
      "<ACF3531A>": "",
      "<9EE99B1E>": 33024,
      "<2B51649C>": 16513,
      "<C1A03E98>": 1072,
      "<554EE944>": 124,
      "<DBAF43F0>": "I reckon that's the case, anyhow."
    },
    {
      "$id": 39,
      "<8C7DD24D>": "<F547DDD0>",
      "<ACF3531A>": "",
      "<9EE99B1E>": 33024,
      "<2B51649C>": 16513,
      "<C1A03E98>": 1072,
      "<554EE944>": 124,
      "<DBAF43F0>": "Makes you think. We could learn from them."
    },
    {
      "$id": 40,
      "<8C7DD24D>": "<D6A78F2E>",
      "<ACF3531A>": "",
      "<9EE99B1E>": 33024,
      "<2B51649C>": 16513,
      "<C1A03E98>": 1072,
      "<554EE944>": 124,
      "<DBAF43F0>": "Yeah."
    }
  ]
}